mkdocs_bibtex/__init__.py
mkdocs_bibtex/plugin.py
mkdocs_bibtex/utils.py
mkdocs_bibtex_recursive-2.8.15.dist-info/LICENSE
mkdocs_bibtex_recursive-2.8.15.dist-info/METADATA
mkdocs_bibtex_recursive-2.8.15.dist-info/WHEEL
mkdocs_bibtex_recursive-2.8.15.dist-info/entry_points.txt
mkdocs_bibtex_recursive-2.8.15.dist-info/top_level.txt
mkdocs_bibtex_recursive-2.8.15.dist-info/RECORD
