Metadata-Version: 2.1
Name: mkdocs-bibtex-recursive
Version: 2.8.15
Summary: An MkDocs plugin that enables managing citations with BibTex
Home-page: https://github.com/shyamd/mkdocs-bibtex/
Author: Shyam Dwaraknath
Author-email: shyamd@lbl.gov
License: BSD-3-Clause-LBNL
Keywords: mkdocs python markdown bibtex
Requires-Python: >=3.6
License-File: LICENSE
Requires-Dist: mkdocs (>=1)
Requires-Dist: pybtex (>=0.22)
Requires-Dist: pypandoc (>=1.5)
Requires-Dist: requests (>=2.8.1)
Requires-Dist: validators (>=0.19.0)
